peak_performance/__init__.py
peak_performance/models.py
peak_performance/pipeline.py
peak_performance/plots.py
peak_performance/test_main.py
peak_performance/test_models.py
peak_performance/test_pipeline.py
peak_performance/test_plots.py
peak_performance-0.7.1.dist-info/LICENSE.md
peak_performance-0.7.1.dist-info/METADATA
peak_performance-0.7.1.dist-info/WHEEL
peak_performance-0.7.1.dist-info/top_level.txt
peak_performance-0.7.1.dist-info/RECORD
