Metadata-Version: 2.1
Name: peak-performance
Version: 0.7.1
Summary: A Python toolbox to fit chromatography peaks with uncertainty.
Author-email: Jochen Nießer <j.niesser@fz-juelich.de>, Michael Osthege <m.osthege@fz-juelich.de>
License: AGPLv3
Project-URL: homepage, https://jugit.fz-juelich.de/IBG-1/micropro/peak-performance
Project-URL: documentation, https://jugit.fz-juelich.de/IBG-1/micropro/peak-performance
Project-URL: repository, https://jugit.fz-juelich.de/IBG-1/micropro/peak-performance
Keywords: hplc,mass-spectrometry,uncertainty quantification
Classifier: Programming Language :: Python :: 3
Classifier: Operating System :: OS Independent
Classifier: License :: OSI Approved :: GNU Affero General Public License v3
Classifier: Intended Audience :: Science/Research
Requires-Python: >=3.9
License-File: LICENSE.md
Requires-Dist: arviz
Requires-Dist: matplotlib
Requires-Dist: numpy
Requires-Dist: pandas
Requires-Dist: pymc>=5.9.1
Requires-Dist: pytensor
Requires-Dist: scipy
Requires-Dist: openpyxl
